auden/__init__.py
auden-0.0.0.dev0.dist-info/METADATA
auden-0.0.0.dev0.dist-info/WHEEL
auden-0.0.0.dev0.dist-info/top_level.txt
auden-0.0.0.dev0.dist-info/RECORD
